py_pursuit_pathing/2018-field.gif
py_pursuit_pathing/__init__.py
py_pursuit_pathing/mathlib.py
py_pursuit_pathing/motion_profile.py
py_pursuit_pathing/plot_arcs.py
py_pursuit_pathing/plot_curves.py
py_pursuit_pathing/plot_splines.py
py_pursuit_pathing/plotter.py
py_pursuit_pathing/pose.py
py_pursuit_pathing/pursuit.py
py_pursuit_pathing/spline_designer.py
py_pursuit_pathing/splines.py
py_pursuit_pathing-0.0.2.dist-info/LICENSE.txt
py_pursuit_pathing-0.0.2.dist-info/METADATA
py_pursuit_pathing-0.0.2.dist-info/RECORD
py_pursuit_pathing-0.0.2.dist-info/WHEEL
py_pursuit_pathing-0.0.2.dist-info/top_level.txt
