Metadata-Version: 2.1
Name: py-pursuit-pathing
Version: 0.0.2
Summary: Path following using pure pursuit
Home-page: https://github.com/nickschatz/purepursuit
Author: Nick Schatz
Author-email: nick@nickschatz.com
License: MIT
Platform: UNKNOWN
Classifier: Development Status :: 3 - Alpha
Classifier: Intended Audience :: Developers
Classifier: Topic :: Software Development :: Libraries
Classifier: License :: OSI Approved :: MIT License
Classifier: Programming Language :: Python :: 3.6
Requires-Python: >=3.6
Requires-Dist: numpy
